nti_sphinx_questions/__init__.py
nti_sphinx_questions/tests/__init__.py
nti_sphinx_questions/tests/test_import.py
nti_sphinx_questions-0.0.1.dist-info/LICENSE
nti_sphinx_questions-0.0.1.dist-info/METADATA
nti_sphinx_questions-0.0.1.dist-info/WHEEL
nti_sphinx_questions-0.0.1.dist-info/top_level.txt
nti_sphinx_questions-0.0.1.dist-info/zip-safe
nti_sphinx_questions-0.0.1.dist-info/RECORD
